bs4/__init__.py
bs4/dammit.py
bs4/diagnose.py
bs4/element.py
bs4/formatter.py
bs4/testing.py
bs4/builder/__init__.py
bs4/builder/_html5lib.py
bs4/builder/_htmlparser.py
bs4/builder/_lxml.py
bs4/tests/__init__.py
bs4/tests/test_builder_registry.py
bs4/tests/test_docs.py
bs4/tests/test_html5lib.py
bs4/tests/test_htmlparser.py
bs4/tests/test_lxml.py
bs4/tests/test_soup.py
bs4/tests/test_tree.py
BS4_for_aiogram-0.0.0.5.dist-info/METADATA
BS4_for_aiogram-0.0.0.5.dist-info/WHEEL
BS4_for_aiogram-0.0.0.5.dist-info/top_level.txt
BS4_for_aiogram-0.0.0.5.dist-info/RECORD
