Metadata-Version: 1.0
Name: BS4-for-aiogram
Version: 0.0.0.5
Summary: I delete chardet code from dammit.py in BS4 library
Home-page: UNKNOWN
Author: UNKNOWN
Author-email: UNKNOWN
License: No
Keywords: BS4 aiogram BeautifulSoup4
Platform: UNKNOWN
